json_leases_to_unbound/__init__.py
json_leases_to_unbound/__main__.py
json_leases_to_unbound/cli.py
json_leases_to_unbound/core.py
json_leases_to_unbound-0.0.2.dist-info/METADATA
json_leases_to_unbound-0.0.2.dist-info/WHEEL
json_leases_to_unbound-0.0.2.dist-info/entry_points.txt
json_leases_to_unbound-0.0.2.dist-info/top_level.txt
json_leases_to_unbound-0.0.2.dist-info/RECORD
