Metadata-Version: 2.4
Name: json-leases-to-unbound
Version: 0.0.2
Summary: Monitor JSON lease files and sync them to Unbound DNS server
Author-email: Junior <cjuniorfox@gmail.com>
License: MIT
Project-URL: Homepage, https://github.com/junior/json-leases-to-unbound
Project-URL: Repository, https://github.com/junior/json-leases-to-unbound
Project-URL: Issues, https://github.com/junior/json-leases-to-unbound/issues
Classifier: Development Status :: 3 - Alpha
Classifier: Intended Audience :: System Administrators
Classifier: Topic :: System :: Networking :: Monitoring
Classifier: License :: OSI Approved :: MIT License
Classifier: Programming Language :: Python :: 3
Classifier: Programming Language :: Python :: 3.8
Classifier: Programming Language :: Python :: 3.9
Classifier: Programming Language :: Python :: 3.10
Classifier: Programming Language :: Python :: 3.11
Classifier: Programming Language :: Python :: 3.12
Requires-Python: >=3.8
Requires-Dist: watchdog<3.0,>=2.1.9
Provides-Extra: test
Requires-Dist: pytest>=7.0.0; extra == "test"
Requires-Dist: pytest-mock>=3.10.0; extra == "test"
Requires-Dist: pytest-cov>=4.0.0; extra == "test"
